{
  "result": [
    {
      "id": 0,
      "title": "Останнє з медійного архіву «KLIO»",
      "details": [
        {
          "adult": false,
          "backdrop_path": "/background_78.jpg",
          "genre_ids": [
          ],
          "id": 13,
          "isKlio": true,
          "original_language": "hi",
          "original_title": "महाभारत (Mahabharat)",
          "overview": "Індійській телесеріал, заснований на давньоіндійському епосі «Магабга́рата», найкраща його екранізація.",
          "popularity": 0,
          "poster_path": "/13-Mahabharata.jpg",
          "release_date": "2013-09-24",
          "tagline": "",
          "title": "Магабгарата",
          "video": false,
          "vote_average": 0,
          "vote_count": 0
        },
        {
          "adult": false,
          "backdrop_path": "/background_77.jpg",
          "genre_ids": [
          ],
          "id": 7,
          "isKlio": true,
          "original_language": "fr",
          "original_title": "Іноземні фільми українською",
          "overview": "Художні фільми різних країн світу, що були озвучені українською мовою професійними акторами.",
          "popularity": 0,
          "poster_path": "/7-Inozemni_filmy_ukrainskoiu.jpg",
          "release_date": "2009-07-29",
          "tagline": "",
          "title": "Іноземні фільми українською",
          "video": false,
          "vote_average": 0,
          "vote_count": 0
        },
        {
          "adult": false,
          "backdrop_path": "/background_75.jpg",
          "genre_ids": [
          ],
          "id": 4,
          "isKlio": true,
          "original_language": "de",
          "original_title": "Фільми з субтитрами",
          "overview": "Іноземні художні фільми, де у якості перекладу застосоване субтитрування українською мовою.",
          "popularity": 0,
          "poster_path": "/4-Filmy_z_subtytramy.jpg",
          "release_date": "1921-04-07",
          "tagline": "",
          "title": "Фільми з субтитрами",
          "video": false,
          "vote_average": 0,
          "vote_count": 0
        },
        {
          "adult": false,
          "backdrop_path": "/background_72.jpg",
          "genre_ids": [
          ],
          "id": 6,
          "isKlio": true,
          "original_language": "en",
          "original_title": "36 Crazyfists",
          "overview": "36 Crazyfists - американський метал-гурт. Назва гурту походить із фільму \"Джекі Чан та 36 божевільних кулаків\".",
          "popularity": 0,
          "poster_path": "/6-36_Crazyfists.jpg",
          "release_date": "2008-04-14",
          "tagline": "",
          "title": "36 Crazyfists",
          "video": false,
          "vote_average": 0,
          "vote_count": 0
        },
        {
          "adult": false,
          "backdrop_path": "/background_71.jpg",
          "genre_ids": [
          ],
          "id": 3,
          "isKlio": true,
          "original_language": "en",
          "original_title": "3 Inches of Blood",
          "overview": "3 Inches of Blood (укр. 3 дюйми крові) - канадський геві-метал-гурт, створений 1999 року у місті Вікторія (провінція Британська Колумбія). Головною відмінністю цього гурту є наявність двох вокалістів.",
          "popularity": 0,
          "poster_path": "/3-3_Inches_of_Blood.jpg",
          "release_date": "2007-04-13",
          "tagline": "",
          "title": "3 Inches of Blood",
          "video": false,
          "vote_average": 0,
          "vote_count": 0
        },
        {
          "adult": false,
          "backdrop_path": "/background_70.jpg",
          "genre_ids": [
          ],
          "id": 2,
          "isKlio": true,
          "original_language": "uk",
          "original_title": "Емма Андієвська",
          "overview": "Емма Іванівна Андієвська — українська письменниця, поетеса та художниця, що працює у стилі сюрреалізму.",
          "popularity": 0,
          "poster_path": "/2-Emma_Andiievska.jpg",
          "release_date": "2013-07-19",
          "tagline": "",
          "title": "Емма Андієвська",
          "video": false,
          "vote_average": 0,
          "vote_count": 0
        },
        {
          "adult": false,
          "backdrop_path": "/background_68.jpg",
          "genre_ids": [
          ],
          "id": 15,
          "isKlio": true,
          "original_language": "uk",
          "original_title": "Українські державники",
          "overview": "Серія документальних фільмів, які розповідають про найвідоміших творців української державності.",
          "popularity": 0,
          "poster_path": "/15-Ukrainski_derzhavnyky.jpg",
          "release_date": "2006-01-28",
          "tagline": "",
          "title": "Українські державники",
          "video": false,
          "vote_average": 0,
          "vote_count": 0
        },
        {
          "adult": false,
          "backdrop_path": "/background_66.jpg",
          "genre_ids": [
          ],
          "id": 17,
          "isKlio": true,
          "original_language": "uk",
          "original_title": "Непрощені",
          "overview": "Серія документальних фільмів про українських діячів, які були оббрехані комуністичною пропагандою.",
          "popularity": 0,
          "poster_path": "/17-Neproshcheni.jpg",
          "release_date": "2007-04-04",
          "tagline": "",
          "title": "Непрощені",
          "video": false,
          "vote_average": 0,
          "vote_count": 0
        },
        {
          "adult": false,
          "backdrop_path": "/background_64.jpg",
          "genre_ids": [
          ],
          "id": 9,
          "isKlio": true,
          "original_language": "uk",
          "original_title": "Невідома Україна. Нариси нашої історії",
          "overview": "Якою мірою виміряти трагедію народу, у якого відібрали історичну пам'ять? Ця проблема лежить в основі фільму.",
          "popularity": 0,
          "poster_path": "/9-Nevidoma_Ukraina_Narysy_nashoi_istorii.jpg",
          "release_date": "1993-01-27",
          "tagline": "",
          "title": "Невідома Україна. Нариси нашої історії",
          "video": false,
          "vote_average": 0,
          "vote_count": 0
        },
        {
          "adult": false,
          "backdrop_path": "/background_63.jpg",
          "genre_ids": [
          ],
          "id": 10,
          "isKlio": true,
          "original_language": "uk",
          "original_title": "Документальні фільми з історії України",
          "overview": "Документальні фільми про українську історію.",
          "popularity": 0,
          "poster_path": "/10-Dokumentalni_filmy_z_istorii_Ukrainy.jpg",
          "release_date": "2007-02-21",
          "tagline": "",
          "title": "Документальні фільми з історії України",
          "video": false,
          "vote_average": 0,
          "vote_count": 0
        },
        {
          "adult": false,
          "backdrop_path": "/background_61.jpg",
          "genre_ids": [
          ],
          "id": 1,
          "isKlio": true,
          "original_language": "uk",
          "original_title": "Велич особистості",
          "overview": "Культурологічний проєкт \"Велич особистости\" ‒ авторський цикл відомого мовознавця, доктора філологічних наук Ірини Фаріон. Проєкт мав на меті розкрити Велич української особистости та знаковість історичних подій, що ставали символом українства всупереч надскладним суспільним обставинам.",
          "popularity": 0,
          "poster_path": "/1-Velych_osobystosti.jpg",
          "release_date": "2015-02-15",
          "tagline": "",
          "title": "Велич особистості",
          "video": false,
          "vote_average": 0,
          "vote_count": 0
        },
        {
          "adult": false,
          "backdrop_path": "/background_59.jpg",
          "genre_ids": [
          ],
          "id": 12,
          "isKlio": true,
          "original_language": "uk",
          "original_title": "Золотий глобус",
          "overview": "Серія чудових путівників «Золотий глобус» допоможе вам побувати у всіх частинах світу, познайомитися з історією, культурою і звичаями інших народів, своїми очима побачити дива природи, що захоплюють дух, і чудові пам'ятки старовини.",
          "popularity": 0,
          "poster_path": "/12-Zolotyy_hlobus.jpg",
          "release_date": "2008-02-09",
          "tagline": "",
          "title": "Золотий глобус",
          "video": false,
          "vote_average": 0,
          "vote_count": 0
        },
        {
          "adult": false,
          "backdrop_path": "/background_58.jpg",
          "genre_ids": [
          ],
          "id": 8,
          "isKlio": true,
          "original_language": "uk",
          "original_title": "Тарас Шевченко. Заповіт",
          "overview": "Кiносерiал про життя i творчiсть Тараса Шевченка. Детальна бiографiя життя i творчостi Тараса Шевченка.",
          "popularity": 0,
          "poster_path": "/8-Taras_Shevchenko_Zapovit.jpg",
          "release_date": "1994-03-27",
          "tagline": "",
          "title": "Тарас Шевченко. Заповіт",
          "video": false,
          "vote_average": 0,
          "vote_count": 0
        },
        {
          "adult": false,
          "backdrop_path": "/background_56.jpg",
          "genre_ids": [
          ],
          "id": 11,
          "isKlio": true,
          "original_language": "en",
          "original_title": "Гаррі Поттер",
          "overview": "Гаррі Поттер — це британсько-американська серія фільмів на основі романів авторства Джоан Роулінг.",
          "popularity": 0,
          "poster_path": "/11-Harri_Potter.jpg",
          "release_date": "2005-11-06",
          "tagline": "",
          "title": "Гаррі Поттер",
          "video": false,
          "vote_average": 0,
          "vote_count": 0
        }
      ]
    },
    {
      "id": 4,
      "title": "Останні фільми",
      "details": [
        {
          "adult": false,
          "backdrop_path": "/7g1zO5t0bd27Iqn5ZUDJmksOGPJ.jpg",
          "genre_ids": [
            18,
            9648,
            37
          ],
          "id": 273248,
          "isKlio": false,
          "original_language": "en",
          "original_title": "The Hateful Eight",
          "overview": "США після Громадянської війни. Легендарний мисливець за головами Джон Рут по кличці Вішатель конвоює ув'язнену. По дорозі до них прибивається ще один мисливець. Снігова буря змушує всіх трьох шукати укриття в крамниці на відшибі, де вже розташувалася вельми строката компанія: генерал, шериф, мексиканець, француз і ковбой ... І один з них - не той, за кого себе видає.",
          "popularity": 42.446,
          "poster_path": "/zUyaTFzXhk8HTJlwi6zwzjukCIQ.jpg",
          "release_date": "2015-12-25",
          "tagline": "Без серйозної причини сюди не лізуть",
          "title": "Мерзенна вісімка",
          "video": false,
          "vote_average": 7.75,
          "vote_count": 13805
        },
        {
          "adult": false,
          "backdrop_path": "/uovH5k4BAEPqXqxgwVrTtqH169g.jpg",
          "genre_ids": [
            878,
            28
          ],
          "id": 373571,
          "isKlio": false,
          "original_language": "en",
          "original_title": "Godzilla: King of the Monsters",
          "overview": "Історія розказує про героїчні зусилля криптозоологічного агентства «Монарх», яке намагається стримати гігантських монстрів. Цього разу проти могутнього Ѓодзілли виступають Мотра, Родан та ультимативний кайдзю — триголовий монстр Кінг Гідора. Коли ці древні суперхижаки, які з плином часу перетворились на напівзабуті міфи, повстають знову, щоб зійтись у протистоянні, людству тільки й лишається, що відійти в сторону та намагатись не загинути.",
          "popularity": 101.868,
          "poster_path": "/oQ8vuEjW32WlmdJb0vOP9ERDZuu.jpg",
          "release_date": "2019-05-29",
          "tagline": "Хай живе король.",
          "title": "Ґодзілла II: Король монстрів",
          "video": false,
          "vote_average": 6.701,
          "vote_count": 5933
        },
        {
          "adult": false,
          "backdrop_path": "/ngBFDOsx13sFXiMweDoL54XYknR.jpg",
          "genre_ids": [
            53,
            18,
            878
          ],
          "id": 450465,
          "isKlio": false,
          "original_language": "en",
          "original_title": "Glass",
          "overview": "Небезпечний псих з множинним розладом особистості і таємничий терорист на ім’я «Скло» виходять на слід своїх давніх ворогів. Хто зупинить Звіра в людській подобі?",
          "popularity": 59.792,
          "poster_path": "/6mhShhClTJdfcbRN49Z13raPHSe.jpg",
          "release_date": "2019-01-16",
          "tagline": "",
          "title": "Скло",
          "video": false,
          "vote_average": 6.678,
          "vote_count": 8167
        },
        {
          "adult": false,
          "backdrop_path": "/9pkZesKMnblFfKxEhQx45YQ2kIe.jpg",
          "genre_ids": [
            27,
            53
          ],
          "id": 381288,
          "isKlio": false,
          "original_language": "en",
          "original_title": "Split",
          "overview": "Кевін страждає від психічного розладу: у його тілі живуть понад 23 різних особистості. Одна з них змушує хлопця викрасти і утримувати в полоні трьох молодих дівчат. Демон в людській подобі терзає і грається з полонянками, готуючи їх до пришестя Звіра.",
          "popularity": 367.475,
          "poster_path": "/jsV9IFoRBgxJKgzd77EDY5PnzjR.jpg",
          "release_date": "2017-01-19",
          "tagline": "23 особистості в одному тілі. 24-та рветься назовні.",
          "title": "Спліт",
          "video": false,
          "vote_average": 7.344,
          "vote_count": 16913
        },
        {
          "adult": false,
          "backdrop_path": "/mWLljCmpqlcYQh7uh51BBMwCZwN.jpg",
          "genre_ids": [
            27,
            53,
            9648
          ],
          "id": 522681,
          "isKlio": false,
          "original_language": "en",
          "original_title": "Escape Room",
          "overview": "Групі людей пропонують взяти участь у квесті, переможцю обіцяють велику суму грошей. Герої погоджуються, але, почавши грати, розуміють, що не все так просто, і вони повинні задіяти усі знання та навички заради виживання.",
          "popularity": 46.813,
          "poster_path": "/wLSlMJfYRFebz39qlhMiIPYUEml.jpg",
          "release_date": "2019-01-03",
          "tagline": "Знайди ключ, щоб вижити.",
          "title": "Смертельний лабіринт",
          "video": false,
          "vote_average": 6.538,
          "vote_count": 4511
        },
        {
          "adult": false,
          "backdrop_path": "/A7CYNTa3fWyU0t207XiecgriQv5.jpg",
          "genre_ids": [
            53,
            18,
            9648
          ],
          "id": 9741,
          "isKlio": false,
          "original_language": "en",
          "original_title": "Unbreakable",
          "overview": "О 15:15 відбувається страшна залізнична катастрофа. Із 132 пасажирів вижив лише один. Девід Данн не просто вцілів посеред миттєвого пекла із заліза та вогню — він не отримав жодної подряпини. І лише одна людина на землі знає причину цього дива — Елайджа Прайс на прізвисько «Містер Скло», чиї кістки можуть зламатися навіть від незначного зовнішнього зусилля, і який впевнений, що Данн володiє надлюдськими здiбностями...",
          "popularity": 88.007,
          "poster_path": "/t1m3a0JgHl2AdhFtQzrCoQlvhip.jpg",
          "release_date": "2000-11-22",
          "tagline": "",
          "title": "Невразливий",
          "video": false,
          "vote_average": 7.142,
          "vote_count": 8981
        },
        {
          "adult": false,
          "backdrop_path": "/3P52oz9HPQWxcwHOwxtyrVV1LKi.jpg",
          "genre_ids": [
            28,
            35,
            12
          ],
          "id": 383498,
          "isKlio": false,
          "original_language": "en",
          "original_title": "Deadpool 2",
          "overview": "Найкращий балакучий найманець повертається на екрани. Він уже помстився всім, кому хотів, за те, що з ним зробили. Тепер він просто шукає свій втрачений смак до життя, попутно лупцює різні дупи, б'ється з ніндзя, якудзою й іншими цікавими істотами. А тут ще з майбутнього прибуває суперсолдат Кейбл, у якого місія – убивати. Ще цю велику дупу потрібно зупинити. У той же час Вейд Вілсон задумався про важливість сім'ї та дружби.",
          "popularity": 333.549,
          "poster_path": "/lcwlZ9MyzDTHPAsSTSAsI1jP9sS.jpg",
          "release_date": "2018-05-10",
          "tagline": "Готуйся до більшого.",
          "title": "Дедпул 2",
          "video": false,
          "vote_average": 7.487,
          "vote_count": 17086
        },
        {
          "adult": false,
          "backdrop_path": "/y7N6wRWVLxtm7p9HPKZdmcFHIMQ.jpg",
          "genre_ids": [
            12,
            35,
            10751,
            14
          ],
          "id": 420814,
          "isKlio": false,
          "original_language": "en",
          "original_title": "Christopher Robin",
          "overview": "Улюблений герой кількох поколінь Крістофер Робін на порозі грандіозної пригоди! Хлопець виріс і тепер у його світі немає місця для польоту фантазії та нескінченних ігор – бізнес відбирає Крістофера навіть у власної родини. Та одного дня все зміниться...  Несподівано у його житті з’являється друг дитинства – неповторний Вінні-пух…",
          "popularity": 30.79,
          "poster_path": "/okIxPVUeLHdHOCok27h5n4DUZ4C.jpg",
          "release_date": "2018-08-01",
          "tagline": "Минуле знайде тебе",
          "title": "Крістофер Робін",
          "video": false,
          "vote_average": 7.319,
          "vote_count": 2635
        },
        {
          "adult": false,
          "backdrop_path": "/5a7lMDn3nAj2ByO0X1fg6BhUphR.jpg",
          "genre_ids": [
            12,
            28,
            878
          ],
          "id": 333339,
          "isKlio": false,
          "original_language": "en",
          "original_title": "Ready Player One",
          "overview": "Події фільму відбуваються у 2045 році, коли світ стоїть на межі хаосу. Люди шукають порятунку в ОАЗІ, дорогій системі віртуальної реальності, створеній геніальним та ексцентричним Джеймсом Голлідеєм. Коли Голлідей помирає, він залишає усі свої величезні статки людині, яка знайде Великоднє яйце, сховане десь в ОАЗІ. Відтоді увесь світ занурюється у цей неймовірний квест. Коли юнак на ім’я Вейд Воттс вирішує приєднатись до змагання, він потрапляє у небезпечне полювання на скарб у фантастичному всесвіті таємниць, відкриттів та ризику.",
          "popularity": 54.408,
          "poster_path": "/vb9TgeWJzK3KUBYpX6jTrC1F4hs.jpg",
          "release_date": "2018-03-28",
          "tagline": "Краща реальність чекає.",
          "title": "Першому гравцю приготуватися",
          "video": false,
          "vote_average": 7.6,
          "vote_count": 15089
        },
        {
          "adult": false,
          "backdrop_path": "/jYlCDS4ecOJWiPSrhC9ce9KM4Fh.jpg",
          "genre_ids": [
            10749,
            18,
            35
          ],
          "id": 493900,
          "isKlio": false,
          "original_language": "de",
          "original_title": "303",
          "overview": "303 — номер моделі автомобіля «Мерседес», що з'єднав двох молодих попутників — студентки Юлі і студента Яна. За сюжетом, 24-річна студентка відправляється в автомобільну подорож через всю Європу на зустріч зі своїм хлопцем. По дорозі вона підсаджує попутника — студента-політолога Яна. Вдень і вночі вони обговорюють глобальні питання, починаючи з політичного балансу сил, проблеми цивілізаційного протистояння «Схід-Захід», кризу комуністичних ідей і провалом соціалістичної експансії. Спільні інтереси змінюються симпатіями, а згодом переростають в кохання…",
          "popularity": 9.636,
          "poster_path": "/3vhdWax2AJg8tS1VrFhjEbKQFy9.jpg",
          "release_date": "2018-12-06",
          "tagline": "",
          "title": "303",
          "video": false,
          "vote_average": 7.392,
          "vote_count": 120
        },
        {
          "adult": false,
          "backdrop_path": "/mDfJG3LC3Dqb67AZ52x3Z0jU0uB.jpg",
          "genre_ids": [
            12,
            28,
            878
          ],
          "id": 299536,
          "isKlio": false,
          "original_language": "en",
          "original_title": "Avengers: Infinity War",
          "overview": "Поки Месники та їхні союзники продовжували захищати світ від загроз, надто великих для героїв поодинці, із космічних тіней виникла нова небезпека: Танос. Деспот міжгалактичної ганебності, його мета - зібрати всі шість Камнів Вічності, артефакти немислимої сили, і використати їх, щоб накласти свою перекручену волю на всю реальність. Все, за що боролися Месники, призвело до цього моменту - доля Землі та самого існування ніколи не була більш невизначеною.",
          "popularity": 289.148,
          "poster_path": "/uUAD59mJPtbqRZa3eFRPsqFdYhM.jpg",
          "release_date": "2018-04-25",
          "tagline": "Цілий всесвіт. Раз і назавжди.",
          "title": "Месники: Війна нескінченності",
          "video": false,
          "vote_average": 8.247,
          "vote_count": 28912
        },
        {
          "adult": false,
          "backdrop_path": "/m7DIYdiOiz57ukZlhWtYp9rDzPT.jpg",
          "genre_ids": [
            18
          ],
          "id": 519010,
          "isKlio": false,
          "original_language": "es",
          "original_title": "Dolor y gloria",
          "overview": "Немолодий режисер оглядається на своє життя і згадує усіх людей, які були важливими для нього і відіграли значущі ролі в його житті. Однак зустрічі з людьми, які були в його минулому, відбудуться не лише в його пам'яті, але й у реальності. Доля підкидає йому сюрпризи та шанс змінити майбутнє.",
          "popularity": 17.689,
          "poster_path": "/2QRVbLPLqNFlZeNeKbjTQhwVIyp.jpg",
          "release_date": "2019-03-22",
          "tagline": "",
          "title": "Біль та слава",
          "video": false,
          "vote_average": 7.4,
          "vote_count": 1723
        },
        {
          "adult": false,
          "backdrop_path": "/2Xe9lISpwXKhvKiHttbFfVRERQX.jpg",
          "genre_ids": [
            18,
            36
          ],
          "id": 490132,
          "isKlio": false,
          "original_language": "en",
          "original_title": "Green Book",
          "overview": "Тоні «Базіка» — людина, яка ніколи не вміла тримати язика за зубами. Але зате у нього досить добре без будь-яких слів виходить махати кулаками. Саме таку людину в 1962 році найняв до себе у водії досить витончений музикант, один із найкращих джазових піаністів свого часу Доктор Дон Ширлі - людина з темною шкірою, але світлою душею. Водій йому потрібен для того, щоб поїхати з концертом на південь, де представників його раси не дуже-то й люблять. Скільки же проблем може виникнути через це. Але ні Тоні, ні Дона це не хвилює, адже є щось більш цінне, що стоїть над кольором шкіри — музика та геніальність Ширлі. Потрібно мати велику мужність, щоб змінювати людей навколо себе.",
          "popularity": 359.368,
          "poster_path": "/nNknZVSxppWPWFtqsu5CXbrlvz2.jpg",
          "release_date": "2018-11-16",
          "tagline": "Натхненний справжньою дружбою",
          "title": "Зелена книга",
          "video": false,
          "vote_average": 8.2,
          "vote_count": 11199
        },
        {
          "adult": false,
          "backdrop_path": "/uHEI6v8ApQusjbaRZ8o7WcLYeWb.jpg",
          "genre_ids": [
            27,
            878,
            53,
            9648
          ],
          "id": 531309,
          "isKlio": false,
          "original_language": "en",
          "original_title": "Brightburn",
          "overview": "Молоде подружжя, яке мешкає в невеличкому провінційному містечку Брайтбьорн, стає свідком падіння інопланетного корабля. У ньому вони знаходять немовля, якого новоспечені батьки відразу ж беруть до себе. Через десять років чи то на тлі пубертатного періоду, чи то від набридлих юнаку докорів, у незвичайного хлопчика прокинуться дивовижні здібності - вони нагадають герою про його винятковість, і він почне вбивати...",
          "popularity": 241.345,
          "poster_path": "/d4Ql6kqaQHRiGbio62zgtUpMNUM.jpg",
          "release_date": "2019-05-09",
          "tagline": "Зло знайшло свого супергероя",
          "title": "Брайтбьорн",
          "video": false,
          "vote_average": 6.132,
          "vote_count": 3010
        },
        {
          "adult": false,
          "backdrop_path": "/xcaSYLBhmDzJ6P14bcKe0KTh3QV.jpg",
          "genre_ids": [
            10402,
            18
          ],
          "id": 424694,
          "isKlio": false,
          "original_language": "en",
          "original_title": "Bohemian Rhapsody",
          "overview": "У центрі сюжету - історія творчого становлення легендарної рок-групи «Queen» і її харизматичного фронтмена - співака Фредді Мерк'юрі. Захоплений музикою студент-художник Фаррух Бульсара з родини емігрантів-парсів грає в групі «Smile», але потім перейменовує її в «Queen» і бере собі псевдонім Фредді Мерк'юрі, під яким він згодом стане відомим на весь світ. Приголомшливий голос, енергетика і харизма молодого співака роблять його одним з найзнаменитіших музикантів XX-го століття, але в житті самого Мерк'юрі відбувається багато потрясінь ...",
          "popularity": 201.427,
          "poster_path": "/aF0YDMwGvxQKzfjemf8xy74C9kS.jpg",
          "release_date": "2018-10-24",
          "tagline": "Більш надзвичайною, ніж їхня музика, є лише його історія.",
          "title": "Богемна рапсодія",
          "video": false,
          "vote_average": 7.987,
          "vote_count": 16491
        },
        {
          "adult": false,
          "backdrop_path": "/sGzuQYSTwJvLBc2PnuSVLHhuFeh.jpg",
          "genre_ids": [
            53,
            9648
          ],
          "id": 401981,
          "isKlio": false,
          "original_language": "en",
          "original_title": "Red Sparrow",
          "overview": "Домініку Єгорову (Дженніфер Лоуренс) проти її волі вербують до російської секретної служби у якості «горобця» - професйної звабниці. Домініка вчиться використовувати своє тіло в якості зброї, але прагне зберегти почуття власної гідності під час проходження цього принизливого вишколу. Перетворившись на знаряддя несправедливої системи, вона стає одним з найцінніших агентів секретної програми. Її першою ціллю є Нат Неш (Джоел Едгертон), офіцер ЦРУ, відповідальний за проникнення американських «кротів» до російської розвідки. Між двома молодими людьми зав’язуються складні стосунки - переплетіння взаємного потягу та омани, які ставлять під загрозу їхню кар’єру, світогляд та безпеку обох держав.",
          "popularity": 224.278,
          "poster_path": "/o5J6Bsrtq5B6WNPArQuzyzfSb0Q.jpg",
          "release_date": "2018-02-28",
          "tagline": "Зваблюй. Обманюй. Повтори.",
          "title": "Червоний горобець",
          "video": false,
          "vote_average": 6.533,
          "vote_count": 5784
        },
        {
          "adult": false,
          "backdrop_path": "/8tqVlaXwF2vbMWMDa909IhdrTRc.jpg",
          "genre_ids": [
            878,
            53
          ],
          "id": 505948,
          "isKlio": false,
          "original_language": "en",
          "original_title": "I Am Mother",
          "overview": "Епідемія знищила життя на Землі. Єдиний шлях до спасіння — бункер, де робот-гуманоїд «Мати» повинен виховати у безпеці дитину. Дівчинка росте здоровою та нічого не потребує. Вона ніколи не виходила назовні та не бачила інших людей, але її не полишають думки про світ, що існує поза межами бункера. Одного разу життя дівчини повністю змінюється, коли на порозі з’являється жінка із проханням про допомогу.",
          "popularity": 282.793,
          "poster_path": "/3y3wGbnJ1k2SSlXHXHPavT9n3qo.jpg",
          "release_date": "2019-06-07",
          "tagline": "",
          "title": "Дитя робота",
          "video": false,
          "vote_average": 6.692,
          "vote_count": 2455
        },
        {
          "adult": false,
          "backdrop_path": "/lL3IVV8ltcMFn9IcfVmuWnlVmDU.jpg",
          "genre_ids": [
            18
          ],
          "id": 487416,
          "isKlio": false,
          "original_language": "fr",
          "original_title": "Une jeunesse dorée",
          "overview": "Молода закохана пара — Роза і її наречений Мішель насолоджуються красивим і безтурботним життям. Кожної ночі вони шукають пригод у нічних клубах та на головних вечірках міста. На одній з вечірок вони знайомляться із дорослою богемною парою багатіїв, які пропонують відчути атмосферу справжньої свободи та любові. Недосвідчені юнаки занурюються у новий світ мрій, спокуси та обману.",
          "popularity": 4.479,
          "poster_path": "/bRwHxi5kbiOhLqbS0wIQWInr9sy.jpg",
          "release_date": "2019-01-16",
          "tagline": "За красиве життя треба платити",
          "title": "Золота молодь",
          "video": false,
          "vote_average": 4.3,
          "vote_count": 25
        },
        {
          "adult": false,
          "backdrop_path": "/aiM3XxYE2JvW1vJ4AC6cI1RjAoT.jpg",
          "genre_ids": [
            28,
            80,
            53,
            35
          ],
          "id": 438650,
          "isKlio": false,
          "original_language": "en",
          "original_title": "Cold Pursuit",
          "overview": "Нельс Коксман — працелюбний батько невеликого сімейства, який працює водієм снігоочисника. У нього є дружина й син, комфортабельний будинок і навіть звання громадянина року. Але все змінюється в одну мить, коли він дізнається, що його син убитий впливовим наркобароном. В ім’я справедливості він починає холоднокровно прибирати бандитів один за одним.",
          "popularity": 49.983,
          "poster_path": "/fTC06PVGuWgACTEVdnwAoXoI8Mx.jpg",
          "release_date": "2019-02-07",
          "tagline": "",
          "title": "Холодна помста",
          "video": false,
          "vote_average": 5.809,
          "vote_count": 2487
        },
        {
          "adult": false,
          "backdrop_path": "/zfbjgQE1uSd9wiPTX4VzsLi0rGG.jpg",
          "genre_ids": [
            18,
            80
          ],
          "id": 278,
          "isKlio": false,
          "original_language": "en",
          "original_title": "The Shawshank Redemption",
          "overview": "Енді Дюфрейна, віцепрезидента солідного банку, засуджують до двох довічних ув’язнень за обвинуваченням у вбивстві дружини та її коханця. Він відбуває ув’язнення в тюрмі Шоушенка, де проходить усі кола пекла, проявляючи незвичайну мужність, завзятість і холоднокровність.",
          "popularity": 123.586,
          "poster_path": "/6BRshOK03BnxTedpAhZl2yZBLTY.jpg",
          "release_date": "1994-09-23",
          "tagline": "Страх триматиме вас у полоні. Надія може вас звільнити.",
          "title": "Втеча з Шоушенка",
          "video": false,
          "vote_average": 8.705,
          "vote_count": 26208
        },
        {
          "adult": false,
          "backdrop_path": "/qAzYK4YPSWDc7aa4R43LcwRIAyb.jpg",
          "genre_ids": [
            28,
            12,
            878
          ],
          "id": 299537,
          "isKlio": false,
          "original_language": "en",
          "original_title": "Captain Marvel",
          "overview": "Історія, дії якої розгортаються у 1990-ті, розповідає про Керол Денверс, яка стає одним з наймогутніших героїв у всесвіті, коли Земля опиняється в самому епіцентрі міжгалактичної війни між двома інопланетними расами. «Капітан Марвел» — це абсолютно нова пригода з раніше небаченого нами періоду історії Marvel.",
          "popularity": 419.979,
          "poster_path": "/4yW6LCKxyU2QFo34S2ULdI4QavQ.jpg",
          "release_date": "2019-03-06",
          "tagline": "Вище. Хоробріше. Сильніше.",
          "title": "Капітан Марвел",
          "video": false,
          "vote_average": 6.8,
          "vote_count": 15285
        },
        {
          "adult": false,
          "backdrop_path": "/aAM3cQmYGjjLQ24m0F0RWfjKQ57.jpg",
          "genre_ids": [
            27,
            18,
            9648
          ],
          "id": 530385,
          "isKlio": false,
          "original_language": "en",
          "original_title": "Midsommar",
          "overview": "Молода пара відправляється відпочити влітку в Швецію. Попутно вони відвідують старого приятеля в невеликому селі, де якраз проходить місцевий фестиваль. Однак незабаром з’ясовується, що за святом сонцестояння Мідсоммар ховається загадковий язичницький культ.",
          "popularity": 61.656,
          "poster_path": "/A68EGr4WVlQdZcXAfyqFzzWP0Ua.jpg",
          "release_date": "2019-07-03",
          "tagline": "Не чіпай лихо, доки воно тихо...",
          "title": "Сонцестояння",
          "video": false,
          "vote_average": 7.161,
          "vote_count": 6744
        },
        {
          "adult": false,
          "backdrop_path": "/8MksSPtPvqcSDruLdpibPmTP7LY.jpg",
          "genre_ids": [
            28,
            53,
            878
          ],
          "id": 280,
          "isKlio": false,
          "original_language": "en",
          "original_title": "Terminator 2: Judgment Day",
          "overview": "Війна роботів і людей продовжується. Здавалося, що людство приречене на повне знищення. Але завдяки своєму лідерові Джону Коннору у опору з'являється шанс перемогти. Не маючи можливості вбити Джона в реальному часі, роботи відправляють в минуле свою саму досконалу розробку - терминатора-вбивцю з рідкого металу, здатного приймати будь-яке обличчя.  Тепер, щоб перемогти в майбутньому, юному Джону Коннор потрібно вижити в сьогоденні. Його шанси істотно підвищуються, коли на допомогу приходить перепрограмований опором термінатор попереднього покоління. Обидва робота вступають в смертельний бій, від результату якого залежить доля людства.",
          "popularity": 135.356,
          "poster_path": "/qpSuIfhRXsM7c8NFB67i8EH9WRI.jpg",
          "release_date": "1991-07-03",
          "tagline": "Нічого особистого",
          "title": "Термінатор 2: Судний день",
          "video": false,
          "vote_average": 8.1,
          "vote_count": 12399
        },
        {
          "adult": false,
          "backdrop_path": "/5tFt6iuGnKapHl5tw0X0cKcnuVo.jpg",
          "genre_ids": [
            10751,
            14,
            12
          ],
          "id": 329996,
          "isKlio": false,
          "original_language": "en",
          "original_title": "Dumbo",
          "overview": "Через свої велетенські вуха незвичайний слоник Дамбо стає посміховиськом для усього цирку. Але вада Дамбо виявляється його секретною суперсилою - вуха дають йому можливість літати!",
          "popularity": 46.76,
          "poster_path": "/68WswvApO91rNR1T6Faw8yez1ZG.jpg",
          "release_date": "2019-03-27",
          "tagline": "Лети до нових вершин",
          "title": "Дамбо",
          "video": false,
          "vote_average": 6.628,
          "vote_count": 4215
        },
        {
          "adult": false,
          "backdrop_path": "/dMWVeuVce8ZLKLI0xpVevihEwm8.jpg",
          "genre_ids": [
            27,
            53
          ],
          "id": 157433,
          "isKlio": false,
          "original_language": "en",
          "original_title": "Pet Sematary",
          "overview": "Моторошна історія за однойменним романом майстра жахів Стівена Кінга. Лікар разом із родиною переїжджає до невеликого містечка й заселяється в будинок поблизу кладовища домашніх тварин. Коли їхнього кота збиває автоцистерна, батько відносить тіло туди, геть не розраховуючи на те, що після поховання кіт оживе в демонічній подобі…",
          "popularity": 191.301,
          "poster_path": "/yqxTFTJ3qmK4EXiQ6Gee0ClvQnT.jpg",
          "release_date": "2019-04-04",
          "tagline": "Іноді краще залишатися мертвим.",
          "title": "Кладовище домашніх тварин",
          "video": false,
          "vote_average": 5.739,
          "vote_count": 3101
        },
        {
          "adult": false,
          "backdrop_path": "/5BkSkNtfrnTuKOtTaZhl8avn4wU.jpg",
          "genre_ids": [
            14,
            27,
            28,
            12
          ],
          "id": 456740,
          "isKlio": false,
          "original_language": "en",
          "original_title": "Hellboy",
          "overview": "Хеллбой вирушає в Англію на зустріч з дружиною Мерліна, Кривавою королевою. Від результату цієї битви залежить доля всього світу.",
          "popularity": 136.475,
          "poster_path": "/9GlR61uFkoeyYZEQmqzObQ9ogrg.jpg",
          "release_date": "2019-04-10",
          "tagline": "Демони також мають демонів",
          "title": "Хеллбой",
          "video": false,
          "vote_average": 5.558,
          "vote_count": 3289
        },
        {
          "adult": false,
          "backdrop_path": "/7RyHsO4yDXtBv1zUU3mTpHeQ0d5.jpg",
          "genre_ids": [
            12,
            878,
            28
          ],
          "id": 299534,
          "isKlio": false,
          "original_language": "en",
          "original_title": "Avengers: Endgame",
          "overview": "Після руйнівних подій \"Месники: Війна нескінченності\", всесвіт перебуває в руїнах завдяки зусиллям Божевільного Титана, Таноса. За допомогою решти союзників Месники повинні зібратися ще раз, щоб скасувати дії Таноса і навести порядок у Всесвіті раз і назавжди, за всяку ціну.",
          "popularity": 261.301,
          "poster_path": "/zwEroaDHpzTcfzJp9WKKXwWAMs.jpg",
          "release_date": "2019-04-24",
          "tagline": "Смерть — частина життя.",
          "title": "Месники: Завершення",
          "video": false,
          "vote_average": 8.254,
          "vote_count": 24904
        },
        {
          "adult": false,
          "backdrop_path": "/oAr5bgf49vxga9etWoQpAeRMvhp.jpg",
          "genre_ids": [
            10402,
            18
          ],
          "id": 504608,
          "isKlio": false,
          "original_language": "en",
          "original_title": "Rocketman",
          "overview": "Фентезійний байопік про одного з найуспішніших виконавців сучасності — неповторного сера Елтона Джона. Історія про те, як музичний вундеркінд перетворився в легенду британського року.",
          "popularity": 169.35,
          "poster_path": "/7lE0pjKl009Ut4tcnRVcSK6PKyx.jpg",
          "release_date": "2019-05-17",
          "tagline": "Його феєрична історія розкривається в його фантазії",
          "title": "Рокетмен",
          "video": false,
          "vote_average": 7.324,
          "vote_count": 4488
        },
        {
          "adult": false,
          "backdrop_path": "/27ZkYMWynuK2qiDP6awc3MsCaOs.jpg",
          "genre_ids": [
            10749,
            18
          ],
          "id": 527641,
          "isKlio": false,
          "original_language": "en",
          "original_title": "Five Feet Apart",
          "overview": "Простір, в якому вони існують, диктує жорстку умову — закохані повинні знаходитися не ближче метра один від одного, їм недоступний навіть дотик. Але справжня любов не знає кордонів, і чим сильніше почуття, тим більша спокуса порушити правила…",
          "popularity": 51.368,
          "poster_path": "/lEsj4fIOthmWccVBLEW6pM1lFG6.jpg",
          "release_date": "2019-03-14",
          "tagline": "",
          "title": "За п’ять кроків до кохання",
          "video": false,
          "vote_average": 8.269,
          "vote_count": 5445
        },
        {
          "adult": false,
          "backdrop_path": "/hgfWu52a8HvC5R4gGbXFRGcC8d4.jpg",
          "genre_ids": [
            27,
            14
          ],
          "id": 553141,
          "isKlio": false,
          "original_language": "en",
          "original_title": "The Head Hunter",
          "overview": "Середньовічний воїн живе відлюдником в похмурому лісі і прагне помститися смертельно небезпечному чудовиську за смерть своєї єдиної дочки. Отримуючи від короля відомості про появу монстрів поблизу, він вирушає за їх головами, щоразу сподіваючись, що зустріне свого заклятого ворога.",
          "popularity": 10.689,
          "poster_path": "/3eKChVBqYlfFgUFci4kIkBqdfDO.jpg",
          "release_date": "2019-04-05",
          "tagline": "",
          "title": "Час монстрів",
          "video": false,
          "vote_average": 5.3,
          "vote_count": 278
        },
        {
          "adult": false,
          "backdrop_path": "/nDP33LmQwNsnPv29GQazz59HjJI.jpg",
          "genre_ids": [
            28,
            12,
            14
          ],
          "id": 447404,
          "isKlio": false,
          "original_language": "en",
          "original_title": "Pokémon Detective Pikachu",
          "overview": "Тім та Пікачу разом вирушають у неймовірну пригоду. Вони шукають ключ до розгадки у неоновому мегаполісі Рима-сіті, де люди та Покемони живуть пліч-о-пліч у неймовірно реалістичному світі. Тім та Пікачу знайомляться з різноманітними Покемонами та дізнаються шокуючу правду, здатну покласти край мирному співіснуванню та поставити під загрозу весь світ Покемонів.",
          "popularity": 41.276,
          "poster_path": "/aM9sCzCXTp34hiFGLe28dXJZtLu.jpg",
          "release_date": "2019-05-03",
          "tagline": "",
          "title": "Покемон. Детектив Пікачу",
          "video": false,
          "vote_average": 6.935,
          "vote_count": 6584
        },
        {
          "adult": false,
          "backdrop_path": "/vVpEOvdxVBP2aV166j5Xlvb5Cdc.jpg",
          "genre_ids": [
            28,
            53,
            80
          ],
          "id": 458156,
          "isKlio": false,
          "original_language": "en",
          "original_title": "John Wick: Chapter 3 - Parabellum",
          "overview": "Джон Вік все ще перебуває в бігах після вбивства члена Високого Столу. $ 14 млн. — глобальний контракт за його голову. Його ціль — вибратися з Нью-Йорка.",
          "popularity": 79.792,
          "poster_path": "/wMAIe7DoD6kvL2VCmXdIHnfMwcT.jpg",
          "release_date": "2019-05-15",
          "tagline": "Кожна дія має свої наслідки",
          "title": "Джон Уік 3",
          "video": false,
          "vote_average": 7.441,
          "vote_count": 10257
        },
        {
          "adult": false,
          "backdrop_path": "/cjRUhKyt2Jo3V1KNzc5tpPNfccG.jpg",
          "genre_ids": [
            878,
            28,
            12
          ],
          "id": 320288,
          "isKlio": false,
          "original_language": "en",
          "original_title": "Dark Phoenix",
          "overview": "Виконуючи смертельно небезпечну рятувальну місію у космосі, Джин Ґрей зазнає впливу якоїсь космічної сили, що перетворює її на одного з найпотужніших мутантів у світі. Борючись із цією дедалі більш мінливою силою і одночасно з власними особистими демонами, Джин стає некерованою, руйнує сім’ю Людей Ікс  і загрожує знищити саму матерію, з якої складається наша планета.",
          "popularity": 369.04,
          "poster_path": "/ArlyaaldKlAV9P5wEI8J19AFzK2.jpg",
          "release_date": "2019-06-05",
          "tagline": "Фенікс вознесеться. Люди Ікс впадуть.",
          "title": "Люди Ікс: Темний Фенікс",
          "video": false,
          "vote_average": 5.978,
          "vote_count": 6268
        },
        {
          "adult": false,
          "backdrop_path": "/2FYzxgLNuNVwncilzUeCGbOQzP7.jpg",
          "genre_ids": [
            35,
            878,
            28
          ],
          "id": 479455,
          "isKlio": false,
          "original_language": "en",
          "original_title": "Men in Black: International",
          "overview": "Люди в чорному, таємна організація на варті спокою та безпеки Землі, вже не раз захищали нас від нападу покидьків Усесвіту. На цей раз найбільша небезпека для світової спільноти, якій агентам доведеться протистояти, — шпигун у їхніх лавах.",
          "popularity": 58.113,
          "poster_path": "/nNR7pzToupxXhKeBZk1xx8Y1ugC.jpg",
          "release_date": "2019-06-12",
          "tagline": "Світ сам себе не врятує.",
          "title": "Люди в чорному: Інтернешнл",
          "video": false,
          "vote_average": 5.92,
          "vote_count": 4709
        },
        {
          "adult": false,
          "backdrop_path": "/aHcNu3tYihvkL45CrXTFY4YfrfF.jpg",
          "genre_ids": [
            35,
            18
          ],
          "id": 429197,
          "isKlio": false,
          "original_language": "en",
          "original_title": "Vice",
          "overview": "Сюжет фільму оповідає про 46-го віце-президента США — Діка Чейні. Дік не тільки став найсильнішим віце-президентом в історії Америки, але і зміг змінити світ.",
          "popularity": 30.331,
          "poster_path": "/ROaVRskhysMdJnIqazU0tXGb4y.jpg",
          "release_date": "2018-12-25",
          "tagline": "Нерозказана реальна історія, яка змінила історію",
          "title": "Влада",
          "video": false,
          "vote_average": 7.036,
          "vote_count": 3225
        },
        {
          "adult": false,
          "backdrop_path": "/oVW0qhssm5NsOqTEJgO9DRH2lYT.jpg",
          "genre_ids": [
            80,
            53
          ],
          "id": 455957,
          "isKlio": false,
          "original_language": "en",
          "original_title": "Domino",
          "overview": "Крістіан, офіцер поліції Копенгагена, прагне помститися за смерть напарника, якого вбив член угруповання ІДІЛ на ім’я Імран. Разом з колегою Крістіан полює на вбивцю. Усе більше заглиблюючись у цю справу, вони ненароком дізнаються про агента ЦРУ, який використовує Імрана, щоб натрапити на слід інших членів терористичного угруповання. Тож тепер Крістіану доводиться рятувати власне життя, а не лише шукати відплати за загиблого колегу.",
          "popularity": 19.007,
          "poster_path": "/f8vNkvlWsPMj9BkoAGPZCNceZhp.jpg",
          "release_date": "2019-05-31",
          "tagline": "",
          "title": "Доміно",
          "video": false,
          "vote_average": 4.653,
          "vote_count": 254
        },
        {
          "adult": false,
          "backdrop_path": "/6IZ84KFhNpy6htsJmwFVuK30pyp.jpg",
          "genre_ids": [
            878,
            28,
            12,
            27,
            53
          ],
          "id": 429471,
          "isKlio": false,
          "original_language": "en",
          "original_title": "Captive State",
          "overview": "Цілих 10 років наша планета вже зовсім не наша... Її захопили інопланетяни, створили тут свою імперію та налагодили свій порядок. Люди в цьому новому світі розділилися на два табори: одні адаптувалися до цих нових правил і всіляко допомагають гостям, які стали господарями. Інші же створили рух опору. Вони готують справжнє повстання, щоб повернути владу людей на Землі. Одні боротимуться за долю нашої планети, інші будуть намагатися вижити, чого би це не коштувало.",
          "popularity": 32.117,
          "poster_path": "/aqfE4dNlDc81vg3LXWFVubDX6i1.jpg",
          "release_date": "2019-03-15",
          "tagline": "Це більше не наша планета",
          "title": "Битва за Землю",
          "video": false,
          "vote_average": 5.6,
          "vote_count": 1101
        },
        {
          "adult": false,
          "backdrop_path": "/pKgP8hG1YlkZg0aHT9HAIg2E9BZ.jpg",
          "genre_ids": [
            28,
            80,
            53
          ],
          "id": 480042,
          "isKlio": false,
          "original_language": "en",
          "original_title": "Escape Plan: The Extractors",
          "overview": "У центрі сюжету — Рей Бреслін, який керує групою фахівців, здатних організувати втечу з будь-якої в’язниці. Він разом зі своєю вірною командою береться розшукати викрадену дочку свого друга — бізнесмена з Гонконгу. Нитки розслідування приводять до однієї з найбільш секретних в’язниць Америки, що називається «Пункт Диявола».",
          "popularity": 18.647,
          "poster_path": "/8dSKVHJG0xLo473BAZpzQjwQWw2.jpg",
          "release_date": "2019-06-20",
          "tagline": "Вихід є завжди",
          "title": "План втечі 3",
          "video": false,
          "vote_average": 5.391,
          "vote_count": 808
        },
        {
          "adult": false,
          "backdrop_path": "/ahNBewkTuhp1ckP42MkKSit0ajX.jpg",
          "genre_ids": [
            28,
            53,
            80,
            9648
          ],
          "id": 535265,
          "isKlio": false,
          "original_language": "en",
          "original_title": "Killers Anonymous",
          "overview": "У таємному кримінальному світі регулярно проходять нічні зустрічі незнайомців, які обговорюють свою загальну залежність — спрагу вбивати. Їх анонімне співтовариство виявляється в центрі темних інтриг, коли все місто приголомшує звістка про замах на сенатора і про жорстоку смерть невдачливого вбивці.",
          "popularity": 16.514,
          "poster_path": "/XoNXGeZSJnOu3ijE8JQFEr8bMM.jpg",
          "release_date": "2019-06-27",
          "tagline": "",
          "title": "Клуб анонімних кілерів",
          "video": false,
          "vote_average": 4.728,
          "vote_count": 189
        },
        {
          "adult": false,
          "backdrop_path": "/i109vzdCkG7W3H9FxHmfpZjgh61.jpg",
          "genre_ids": [
            10751,
            12,
            18
          ],
          "id": 522518,
          "isKlio": false,
          "original_language": "en",
          "original_title": "A Dog's Journey",
          "overview": "Зворушлива історія за мотивами світового бестселера «Життя та мета собаки» отримає продовження. Доля подарує відважному собаці Бейлі нову мету – стати справжнім другом та захисником для онучки свого хазяїна Ітана. Захоплива пригода про любов та дружбу, відданість та надію в неймовірній історії на всі часи.",
          "popularity": 28.331,
          "poster_path": "/xXY6QnIAT48lKvqxNrWC10RpxBJ.jpg",
          "release_date": "2019-05-03",
          "tagline": "Існує дружба, сильніша за час",
          "title": "Подорож хорошого пса",
          "video": false,
          "vote_average": 8.049,
          "vote_count": 1431
        },
        {
          "adult": false,
          "backdrop_path": "/hpgda6P9GutvdkDX5MUJ92QG9aj.jpg",
          "genre_ids": [
            28,
            12,
            35
          ],
          "id": 384018,
          "isKlio": false,
          "original_language": "en",
          "original_title": "Fast & Furious Presents: Hobbs & Shaw",
          "overview": "Закляті супротивники спецагент Гоббс і злочинець Шоу живуть за полярними принципами і ніколи не будуть довіряти один одному. Та у спін-офф культової франшизи «Форсаж» вони змушені об’єднатися, щоб захистити світ від нищівної біологічної атаки.",
          "popularity": 100.441,
          "poster_path": "/aRrOb1PwRpMFIInlPNTEGYnBt5r.jpg",
          "release_date": "2019-08-01",
          "tagline": "Ніщо не міцніше, ніж сім'я.",
          "title": "Форсаж: Гоббс та Шоу",
          "video": false,
          "vote_average": 6.862,
          "vote_count": 6948
        },
        {
          "adult": false,
          "backdrop_path": "/dBt0DoFfbhOI4ypUfRj1uTq623M.jpg",
          "genre_ids": [
            27
          ],
          "id": 521029,
          "isKlio": false,
          "original_language": "en",
          "original_title": "Annabelle Comes Home",
          "overview": "Щоб стримати Анабель від поширення хаосу, демонологи Ед і Лоррейн Воррени ховають одержиму ляльку. Тепер вона лежить під освяченим склом у замкненій кімнаті артефактів у будинку Ворренів. Однак безпросвітна ніч жаху чекає на мешканців будинку, коли Анабель пробуджує злих духів кімнати. Їхньою новою мішенню стає десятирічна дочка Ворренів Джуді і її друзі.",
          "popularity": 55.926,
          "poster_path": "/bXlnA4CLWIss1AgBVli5qSdtU2.jpg",
          "release_date": "2019-06-26",
          "tagline": "",
          "title": "Анабель 3",
          "video": false,
          "vote_average": 6.427,
          "vote_count": 3353
        },
        {
          "adult": false,
          "backdrop_path": "/o7JVhqMmrex1TPbmuxl8YXVlcfl.jpg",
          "genre_ids": [
            28,
            35,
            14
          ],
          "id": 287947,
          "isKlio": false,
          "original_language": "en",
          "original_title": "Shazam!",
          "overview": "14-річний Біллі Бетсон – проблемний підліток, який переходить з однієї прийомної сім'ї в іншу. Від помираючого чарівника хлопець отримує здатність перетворюватись на дорослого супергероя, який поєднує в собі силу шести древніх богів. Не встигнувши опанувати усі свої нові можливості, Біллі змушений буде вступити в двобій зі злим доктором Сіваною ...",
          "popularity": 301.815,
          "poster_path": "/nPzJ8ku1PS3fkusMXMx6Yzs84FQ.jpg",
          "release_date": "2019-03-29",
          "tagline": "Просто скажи це слово.",
          "title": "Шазам!",
          "video": false,
          "vote_average": 7.018,
          "vote_count": 9218
        },
        {
          "adult": false,
          "backdrop_path": "/8RKBHHRqOMOLh5qW3sS6TSFTd8h.jpg",
          "genre_ids": [
            28,
            878,
            12
          ],
          "id": 399579,
          "isKlio": false,
          "original_language": "en",
          "original_title": "Alita: Battle Angel",
          "overview": "XXVI століття. На планеті Земля багатії живуть у Небесному місті, біднота задовольняється життям у Нижньому місті, куди скидаються всі відходи й сміття.  Якось у купі металобрухту Нижнього міста вчений знаходить частини жінки-кіборга й повертає її до життя.  Прийшовши до тями, кіборг виявляє, що з її пам’яті стерто все, крім бойових прийомів. Тепер вона мусить відновити втрачені спогади й з’ясувати, хто відправив її на звалище.",
          "popularity": 134.585,
          "poster_path": "/b6z9WF641mT3qcQ1V1G5GTNmzTX.jpg",
          "release_date": "2019-01-31",
          "tagline": "",
          "title": "Аліта: Бойовий ангел",
          "video": false,
          "vote_average": 7.231,
          "vote_count": 8852
        },
        {
          "adult": false,
          "backdrop_path": "/s6awXOxTKYQLSktiIJfI3969dZH.jpg",
          "genre_ids": [
            35,
            80
          ],
          "id": 449562,
          "isKlio": false,
          "original_language": "en",
          "original_title": "The Hustle",
          "overview": "Блискучі шахрайки та виходять на велике полювання! Одна — витончена грація з холодним розумом, яка завжди зриває куш, інша —  дівчина проста і за мить вичистить ваші кишені. Хто ж з них заволодіє серцем і банківським рахунком нової жертви?",
          "popularity": 44.492,
          "poster_path": "/bSOAjMqEd5p9tDrmMaReEdAETXW.jpg",
          "release_date": "2019-05-09",
          "tagline": "Вони витрусять із поганців трохи грошенят.",
          "title": "Шахрайки",
          "video": false,
          "vote_average": 6.196,
          "vote_count": 2421
        },
        {
          "adult": false,
          "backdrop_path": "/34jW8LvjRplM8Pv06cBFDpLlenR.jpg",
          "genre_ids": [
            28,
            12,
            878
          ],
          "id": 429617,
          "isKlio": false,
          "original_language": "en",
          "original_title": "Spider-Man: Far From Home",
          "overview": "Пітер Паркер намагається жити нормальним життям і вирушає на канікули до Європи. Втім, коли його друзі опиняються в смертельній небезпеці, Людина-павук не вагаючись приходить на допомогу. Могутній ворог на ім’я Містеріо має не лише лихі плани щодо купки підлітків, а й реальні шанси знищити весь світ.",
          "popularity": 85.397,
          "poster_path": "/7kBGsURceVZBdEEk0o6NB2VZxC7.jpg",
          "release_date": "2019-06-28",
          "tagline": "Час зробити крок уперед.",
          "title": "Людина-павук: Далеко від дому",
          "video": false,
          "vote_average": 7.429,
          "vote_count": 15169
        },
        {
          "adult": false,
          "backdrop_path": "/tcheoA2nPATCm2vvXw2hVQoaEFD.jpg",
          "genre_ids": [
            27
          ],
          "id": 346364,
          "isKlio": false,
          "original_language": "en",
          "original_title": "It",
          "overview": "Коли в містечку Деррі, штат Мен, починають пропадати діти, кілька хлопців стикаються зі своїми найбільшими страхами і змушені помірятися силами зі злісним клоуном Пеннивайз, чиї прояви жорстокості і список жертв йдуть в глиб століть.",
          "popularity": 219.434,
          "poster_path": "/o9J4nbNKbedaYzGcng7thyZjfPv.jpg",
          "release_date": "2017-09-06",
          "tagline": "Твої страхи розкриті",
          "title": "Воно",
          "video": false,
          "vote_average": 7.24,
          "vote_count": 18595
        },
        {
          "adult": false,
          "backdrop_path": "/c1YQcpqsljC7lYEmTIeftcl22VS.jpg",
          "genre_ids": [
            53,
            28
          ],
          "id": 484641,
          "isKlio": false,
          "original_language": "fr",
          "original_title": "Anna",
          "overview": "Історія Анни, чия незрівнянна краса приховує вражаючу міць і смертоносний талант найнебезпечнішого найманого вбивці в світі.",
          "popularity": 147.72,
          "poster_path": "/lJBaaVD3vYwHrzUs5ltcMQCU09N.jpg",
          "release_date": "2019-06-19",
          "tagline": "Ніколи не роби зброю мішенню",
          "title": "Анна",
          "video": false,
          "vote_average": 6.712,
          "vote_count": 2591
        }
      ]
    },
    {
      "id": 6,
      "title": "Останні серіали",
      "details": [
        {
          "adult": false,
          "backdrop_path": "/32iacqVElB91YZKl9Ky3QEEkXtH.jpg",
          "genre_ids": [
            10765,
            18,
            9648,
            10759
          ],
          "id": 54671,
          "isKlio": false,
          "original_language": "en",
          "original_title": "Penny Dreadful",
          "overview": "Вікторіанський Лондон. Тут ніколи не було безпечно і спокійно. Городяни зайняті виключно повсякденними справами, не помічаючи ознак прийдешніх змін. Однак їм слід було б стати уважнішими, бо на вулицях британської столиці збирається нечисть самого різного сорту, здатна навести жах на кого завгодно. Із багатьма з представників цієї нечисті ви давно знайомі: тут і демонічний юнак Доріан Ґрей з роману Оскара Вайльда, і доктор Джекіл разом зі своїм альтер-еґо містером Гайдом, і німець Франкенштейн «під ручку» зі своїм жахливим творінням, і спраглий крові граф Дракула із Трансільванії, а також його посіпаки-вампіри та інші, не менш зловісні істоти.",
          "popularity": 248.387,
          "poster_path": "/dMf0e6ecQ6EMOpPBAdZGU3kMfHe.jpg",
          "release_date": "2016-06-19",
          "tagline": "",
          "title": "Бульварні жахіття",
          "video": false,
          "vote_average": 7.84,
          "vote_count": 1270
        },
        {
          "adult": false,
          "backdrop_path": "/iJVgkjFf6TrxDlic97XCkS4fEuc.jpg",
          "genre_ids": [
            18,
            10759
          ],
          "id": 85854,
          "isKlio": false,
          "original_language": "en",
          "original_title": "The Widow",
          "overview": "Серіал про дружину, що вирушає на пошуки свого зниклого чоловіка в ДР Конго.",
          "popularity": 36.924,
          "poster_path": "/f1UCZ21QfcfuOOQGnczTOJWk1dn.jpg",
          "release_date": "2019-02-28",
          "tagline": "",
          "title": "Вдова",
          "video": false,
          "vote_average": 6.9,
          "vote_count": 173
        },
        {
          "adult": false,
          "backdrop_path": "/epq6I0AwVaHldCrQ6xJ5ZsAyHCF.jpg",
          "genre_ids": [
            10765,
            18,
            35
          ],
          "id": 90447,
          "isKlio": false,
          "original_language": "ko",
          "original_title": "호텔 델루나",
          "overview": "Чон Ман Воль проклята за страшний гріх, скоєний нею. Вона приречена керувати готелем примар, аж доки не знайде душу ще більш грішну за її.\n\nТак її життя триває вже 1000 років. Зовні вона мила та привітна, але всередині підступна стара карга, яка ладна на будь-який злочин.\n\nҐу Чан Сан — елітний готель’єр, він молодий та успішний чоловік, який створив себе сам. Досягнувши посади наймолодшого менеджера готельної корпорації, його призначили керувати «Готелем дель Луна» у парі з Ман Воль.",
          "popularity": 58.533,
          "poster_path": "/sRYVPFS4RwqpyVtd0LNq7mIgaA8.jpg",
          "release_date": "2019-08-31",
          "tagline": "",
          "title": "Готель дель Луна",
          "video": false,
          "vote_average": 8.523,
          "vote_count": 511
        },
        {
          "adult": false,
          "backdrop_path": "/eLGICVIbVWke9U8SnUVrtXdwrlC.jpg",
          "genre_ids": [
            80,
            18,
            18
          ],
          "id": 79744,
          "isKlio": false,
          "original_language": "en",
          "original_title": "The Rookie",
          "overview": "Починати з чистого аркуша завжди нелегко, особливо для мешканця маленького містечка Джона Нолана. Після інциденту, який перевернув його життя, він вирішив здійснити давню мрію і приєднатися до поліції Лос-Анджелеса. Старого новачка зустрічають із зрозумілим скептицизмом, проте життєвий досвід, наполегливість та почуття гумору дають Джону перевагу.",
          "popularity": 1579.569,
          "poster_path": "/rN4jJz0OquSHAzNRZGRSa018dgx.jpg",
          "release_date": "2024-05-21",
          "tagline": "",
          "title": "Новобранець",
          "video": false,
          "vote_average": 8.396,
          "vote_count": 1803
        },
        {
          "adult": false,
          "backdrop_path": "/8AdmUPTyidDebwIuakqkSt6u1II.jpg",
          "genre_ids": [
            9648,
            10765,
            18
          ],
          "id": 79242,
          "isKlio": false,
          "original_language": "en",
          "original_title": "Chilling Adventures of Sabrina",
          "overview": "Сабріна намагається знайти справжню себе між своїми натурами смертної та відьми, при цьому їй доведеться протистояти злим силам, які загрожують їй, її сім'ї та всьому світу людей.",
          "popularity": 192.667,
          "poster_path": "/2bkVwv35idEsAO0XMWCitnZeX5i.jpg",
          "release_date": "2020-12-31",
          "tagline": "",
          "title": "Моторошні пригоди Сабріни",
          "video": false,
          "vote_average": 8.219,
          "vote_count": 3443
        },
        {
          "adult": false,
          "backdrop_path": "/2WwhGleN2SGwHptGaLNAmSRLeMf.jpg",
          "genre_ids": [
            35,
            18
          ],
          "id": 89235,
          "isKlio": false,
          "original_language": "en",
          "original_title": "BH90210",
          "overview": "Перезавантаження популярного серіалу 1990-х років «Район Беверлі Гіллс».",
          "popularity": 24.444,
          "poster_path": "/zxrzF4pybdVkR55DyI9PTy5rIlH.jpg",
          "release_date": "2019-09-11",
          "tagline": "",
          "title": "Беверлі Гіллз 90210",
          "video": false,
          "vote_average": 6.755,
          "vote_count": 53
        },
        {
          "adult": false,
          "backdrop_path": "/bs7DjDcvwVH7Hs8rg01VmtAK6RU.jpg",
          "genre_ids": [
            18
          ],
          "id": 85552,
          "isKlio": false,
          "original_language": "en",
          "original_title": "Euphoria",
          "overview": "У центрі історії — 17-річна Ру Беннетт, яка повернулася до рідного дому після лікування в реабілітаційній клініці. Не гаючи часу, вона знову береться за старі звички — наркотики й тусовки. Однак поява в місті дівчини Джулс стає для Ру знаком надії.",
          "popularity": 414.155,
          "poster_path": "/8XwpnqkgYYtCy5XXWYZwYa4SJXa.jpg",
          "release_date": "2022-02-27",
          "tagline": "",
          "title": "Ейфорія",
          "video": false,
          "vote_average": 8.328,
          "vote_count": 9473
        },
        {
          "adult": false,
          "backdrop_path": "/900tHlUYUkp7Ol04XFSoAaEIXcT.jpg",
          "genre_ids": [
            18
          ],
          "id": 87108,
          "isKlio": false,
          "original_language": "en",
          "original_title": "Chernobyl",
          "overview": "Сюжет розгортається 1986 року під час трагічних подій на Чорнобильській АЕС. У центрі уваги – радянський науковець, який має провести розслідування того, що трапилося.",
          "popularity": 99.743,
          "poster_path": "/yRon8r5RbuizP99bVd918LRB8RI.jpg",
          "release_date": "2019-06-03",
          "tagline": "Яка ціна брехні?",
          "title": "Чорнобиль",
          "video": false,
          "vote_average": 8.668,
          "vote_count": 5963
        }
      ]
    },
    {
      "id": 5,
      "title": "Останні мультфільми",
      "details": [
        {
          "adult": false,
          "backdrop_path": "/yjfwNSDljAKsuHwwE34xjlY3tQj.jpg",
          "genre_ids": [
            16,
            14,
            18,
            12
          ],
          "id": 476292,
          "isKlio": false,
          "original_language": "ja",
          "original_title": "さよならの朝に約束の花をかざろう",
          "overview": "Красуня Макія — з роду безсмертних. Упродовж віків багато армій намагалися захопити її народ, щоб заволодіти секретом вічного життя. І ось тепер, коли місто зруйноване, дівчина ховається в лісі. Тут вона зустрічає маленького хлопчика Еріала, який втратив батьків, і починає про нього піклуватися. Проходять роки, хлопчик перетворюється на прекрасного юнака, і в утікачів виникають почуття один до одного. Але Макія розуміє, що Еріал — проста людина, тобто він смертний...",
          "popularity": 32.499,
          "poster_path": "/jGWpICOns9req49uj3pCzUsDoyz.jpg",
          "release_date": "2018-02-24",
          "tagline": "Кохання проти вічності",
          "title": "Прикрась прощальний ранок квітами надії",
          "video": false,
          "vote_average": 8.187,
          "vote_count": 604
        },
        {
          "adult": false,
          "backdrop_path": "/jB5zHG1eHh0OC1S61itXNApZlLD.jpg",
          "genre_ids": [
            12,
            35,
            16
          ],
          "id": 399174,
          "isKlio": false,
          "original_language": "en",
          "original_title": "Isle of Dogs",
          "overview": "Японія, недалеке майбутнє. 12-річним Атарі Кобаяші опікується корумпований мер Мегасакі, з відома якого в місті починається масовий відлов собак — і безпритульних, і домашніх. Тварин відправляють на острів-звалище, куди вже багато років вивозять відходи людської цивілізації. Хлопчик, виявивши пропажу свого пса Спотса, сідає на міні-супер-джет і летить на допомогу чотирилапому другові. Тим часом назріває змова собак-засланців на острові. Хлопчик і собача зграя починають епічну подорож, яка вирішить долю всієї префектури.",
          "popularity": 61.786,
          "poster_path": "/9hNlo0WahTxwQliYNsCB4JCdBAV.jpg",
          "release_date": "2018-03-23",
          "tagline": "Ласкаво просимо до Острову собак",
          "title": "Острів собак",
          "video": false,
          "vote_average": 7.848,
          "vote_count": 4691
        },
        {
          "adult": false,
          "backdrop_path": "/askg3SMvhqEl4OL52YuvdtY40Yb.jpg",
          "genre_ids": [
            10751,
            16,
            10402,
            12
          ],
          "id": 354912,
          "isKlio": false,
          "original_language": "en",
          "original_title": "Coco",
          "overview": "Мігель живе в мексиканському селі в родині шевців і дуже хоче стати музикантом. Щоб здійснити мрію, хлопець має розгадати давню таємницю свого роду, заховану у Країні Мертвих. Отож, взявши в напарники скелета-провідника та дивакуватого пса Данте, Мігель вирушає в потойбіччя…",
          "popularity": 138.041,
          "poster_path": "/aAsWlZmBb5JxQNCwLncswLqY0kk.jpg",
          "release_date": "2017-10-27",
          "tagline": "Святкуй життя",
          "title": "Коко",
          "video": false,
          "vote_average": 8.213,
          "vote_count": 18803
        },
        {
          "adult": false,
          "backdrop_path": "/7t88SoT3Dd8DhGnQuVoSbMNUl3W.jpg",
          "genre_ids": [
            10751,
            16,
            12,
            14
          ],
          "id": 446894,
          "isKlio": false,
          "original_language": "en",
          "original_title": "Smallfoot",
          "overview": "Одного дня молодий розумний єті Міґо знаходить дещо, що всі вважали вигадкою, – людину. Новина про цього «коротконога» дарує Міґо славу та шанс на стосунки з дівчиною його мрій. Крім того, це відкриття неабияк бентежить усіх єті, адже з’ясовується, що поза їхнім невеличким сніговим містечком існує цілий великий світ. І вони пізнають його в запальній історії про дружбу, відвагу та радість відкриттів.",
          "popularity": 27.33,
          "poster_path": "/1JcZljw8lZMEPvhJ3P2bVFGB7Ue.jpg",
          "release_date": "2018-09-20",
          "tagline": "Єті крокують, пригоди віщують.",
          "title": "Смолфут",
          "video": false,
          "vote_average": 6.782,
          "vote_count": 1465
        },
        {
          "adult": false,
          "backdrop_path": "/qDQEQbgP3v7B9IYLAUcYexNrVYP.jpg",
          "genre_ids": [
            10751,
            16,
            35,
            12
          ],
          "id": 404368,
          "isKlio": false,
          "original_language": "en",
          "original_title": "Ralph Breaks the Internet",
          "overview": "На безмежних просторах інтернету є фан на всі смаки: відомі програми, секретні чати, культові меми та герої, кумедне відео та ігри. Здоровань Ральф з такою силою поринає у віртуальний світ, що мережа починає глючити...",
          "popularity": 68.467,
          "poster_path": "/o8BdfxuamaGQvIwGlvcJtN91olk.jpg",
          "release_date": "2018-11-20",
          "tagline": "Хто вирубив інтернет?",
          "title": "Ральф-руйнівник 2: Інтернетрі",
          "video": false,
          "vote_average": 7.191,
          "vote_count": 7319
        },
        {
          "adult": false,
          "backdrop_path": "/b9YkKJcW3pPaXgMZu9uoT7v9yRB.jpg",
          "genre_ids": [
            16,
            28,
            12,
            878
          ],
          "id": 324857,
          "isKlio": false,
          "original_language": "en",
          "original_title": "Spider-Man: Into the Spider-Verse",
          "overview": "Культовий супергерой відтепер у анімації нового покоління! Підліток із Нью-Йорка живе у світі безмежних можливостей Людини-павука, де костюм супергероя носить не лише він.",
          "popularity": 85.621,
          "poster_path": "/lKG7LEVxSSKUJp1zdsPnZV6X1oB.jpg",
          "release_date": "2018-12-06",
          "tagline": "Більш ніж один носить маску.",
          "title": "Людина-павук: Навколо всесвіту",
          "video": false,
          "vote_average": 8.404,
          "vote_count": 15023
        },
        {
          "adult": false,
          "backdrop_path": "/h3KN24PrOheHVYs9ypuOIdFBEpX.jpg",
          "genre_ids": [
            16,
            10751,
            12
          ],
          "id": 166428,
          "isKlio": false,
          "original_language": "en",
          "original_title": "How to Train Your Dragon: The Hidden World",
          "overview": "Нові пригоди давніх друзів – Гикавки та Беззубика. Селищу, де дракони та вікінги живуть у мирі та спокої, загрожує жорстокий ворог. Щоб захистити свій дім, хоробрий правитель Гикавка та його вірний дракон вирушають у подорож до прихованого міфічного світу.",
          "popularity": 58.515,
          "poster_path": "/7QD3hx43BH61vLbxDCQ0IGBlgUQ.jpg",
          "release_date": "2019-01-03",
          "tagline": "Дружба усього життя",
          "title": "Як приборкати дракона 3: Прихований світ",
          "video": false,
          "vote_average": 7.753,
          "vote_count": 6139
        },
        {
          "adult": false,
          "backdrop_path": "/nJyAdKPnW15IAvC6sLBTE0lp6Dv.jpg",
          "genre_ids": [
            35,
            16,
            12,
            10751,
            14
          ],
          "id": 400157,
          "isKlio": false,
          "original_language": "en",
          "original_title": "Wonder Park",
          "overview": "Винахідлива Джун створила модель особливого місця, де панує справжня магія – неймовірного парку атракціонів. Та дівчинка навіть не здогадується, що Диво-парк існує не тільки в її уяві – на неї чекають неймовірні пригоди, нові друзі та важлива місія.",
          "popularity": 25.869,
          "poster_path": "/jBwYxBbZPbuYpUKnoPelZ8pZqlb.jpg",
          "release_date": "2019-03-13",
          "tagline": "Мрій сміливіше!",
          "title": "Диво-парк",
          "video": false,
          "vote_average": 6.5,
          "vote_count": 671
        },
        {
          "adult": false,
          "backdrop_path": "/3EfhschqkWcT4WH7aowAd5d0aen.jpg",
          "genre_ids": [
            10751,
            16
          ],
          "id": 509730,
          "isKlio": false,
          "original_language": "en",
          "original_title": "The Queen's Corgi",
          "overview": "Пригоди Рекса, улюбленого собаки британської королеви. Рекс одного разу втрачає свою господиню з уваги і залишається зовсім один посеред галасливих вулиць. Щоб повернутися додому, Рексу належить зіткнутися зі злими собаками різних порід, закохатися і знайти своє справжнє «я».",
          "popularity": 25.501,
          "poster_path": "/jWkz1wgLZCkdthRRlZFDbPFUsv3.jpg",
          "release_date": "2019-02-13",
          "tagline": "Хвостатий кардинал британського престолу",
          "title": "Королівський корґі",
          "video": false,
          "vote_average": 5.967,
          "vote_count": 405
        },
        {
          "adult": false,
          "backdrop_path": "/UxGdlGzCx5R5FdY8BDM0FQkyKi.jpg",
          "genre_ids": [
            12,
            16,
            35,
            10751
          ],
          "id": 412117,
          "isKlio": false,
          "original_language": "en",
          "original_title": "The Secret Life of Pets 2",
          "overview": "Славетні домашні улюбленці повертаються! Ми й не підозрюємо, скільки усього вони встигають, коли нас немає поруч. Відомі герої і нові «темні конячки», ще більше карколомних пригод і багато пухнастих секретів у комедії для всієї родини!",
          "popularity": 41.018,
          "poster_path": "/3Z6VmTet8OLSOkxWtVkmmZqhg51.jpg",
          "release_date": "2019-05-24",
          "tagline": "В них ще залишились свої секрети",
          "title": "Секрети домашніх тварин 2",
          "video": false,
          "vote_average": 6.958,
          "vote_count": 2912
        },
        {
          "adult": false,
          "backdrop_path": "/2U2h8PpsaWn90jdtyG0tu9ZxttZ.jpg",
          "genre_ids": [
            28,
            12,
            16,
            35,
            10751
          ],
          "id": 280217,
          "isKlio": false,
          "original_language": "en",
          "original_title": "The Lego Movie 2: The Second Part",
          "overview": "Продовження популярної анімаційної комедії «Lego Фільм».",
          "popularity": 26.326,
          "poster_path": "/4E6YZkALsac3KFev9U3k5yxu3c0.jpg",
          "release_date": "2019-02-06",
          "tagline": "Вони приходять шматками.",
          "title": "Lego Фільм 2",
          "video": false,
          "vote_average": 6.681,
          "vote_count": 2092
        },
        {
          "adult": false,
          "backdrop_path": "/93gOZuHazBWulk7b47MCXWVTiqh.jpg",
          "genre_ids": [
            16,
            10402,
            10751,
            35
          ],
          "id": 454458,
          "isKlio": false,
          "original_language": "en",
          "original_title": "UglyDolls",
          "overview": "Якщо ви думаєте, що світ ляльок — це суцільні рожеві хмарки, веселки та єдиноріжки, — ви глибоко помиляєтесь. Знайомтесь — це UGLYDOLLS. Ляльки з характером. У країні UGLYDOLLS гарнюні ляльки намагаються взяти під контроль весь ляльковий світ та витіснити своїх не дуже симпатичних побратимів. Проти такої несправедливості постають відважні друзі з огидними личками, але прекрасними серцями.",
          "popularity": 22.996,
          "poster_path": "/gvAsWoA5qHx9Ht9Aqc7FPfNyNKs.jpg",
          "release_date": "2019-05-01",
          "tagline": "",
          "title": "UglyDolls. Ляльки з характером",
          "video": false,
          "vote_average": 6.6,
          "vote_count": 417
        }
      ]
    },
    {
      "id": 7,
      "title": "Останні мультсеріали",
      "details": [
        {
          "adult": false,
          "backdrop_path": "/qFYDJUIFh8zgEDy3EvnHwhgOl0S.jpg",
          "genre_ids": [
            16,
            35,
            18
          ],
          "id": 61222,
          "isKlio": false,
          "original_language": "en",
          "original_title": "BoJack Horseman",
          "overview": "Американський трагікомедійний серіал розповідає про колишню кінозірку 80-х — початку 90-х років, антропоморфного коня БоДжека, який переживає кризу середнього віку.",
          "popularity": 684.44,
          "poster_path": "/pB9L0jAnEQLMKgexqCEocEW8TA.jpg",
          "release_date": "2020-01-31",
          "tagline": "",
          "title": "Кінь БоДжек",
          "video": false,
          "vote_average": 8.557,
          "vote_count": 2281
        },
        {
          "adult": false,
          "backdrop_path": "/nBrkOZyI75artyizuBFeya48KbO.jpg",
          "genre_ids": [
            16,
            10765
          ],
          "id": 86831,
          "isKlio": false,
          "original_language": "en",
          "original_title": "Love, Death & Robots",
          "overview": "У цій зухвалій антології від Тіма Міллера й Девіда Фінчера чорний гумор переплітається з анімованими історіями про страхітливих істот і божевільні несподіванки.",
          "popularity": 319.394,
          "poster_path": "/90wzmrbwd4KieMUEcMAvE10U8K4.jpg",
          "release_date": "2022-05-20",
          "tagline": "Тріо, на яке ви так довго чекали.",
          "title": "Любов, смерть і роботи",
          "video": false,
          "vote_average": 8.262,
          "vote_count": 3098
        },
        {
          "adult": false,
          "backdrop_path": "/xzjZDyqUobuJtkBljhgLH4Fdnye.jpg",
          "genre_ids": [
            10759,
            16,
            10765,
            35
          ],
          "id": 82684,
          "isKlio": false,
          "original_language": "ja",
          "original_title": "転生したらスライムだった件",
          "overview": "Рімуру Темпест — нове ім’я слизу в фентезійному світі, дане колишньому 37-річному Сатору Мікамі, після того, як його вбив пересічний злодій. Звільнившись від звичайного усталеного ритму минулого життя, він починає свою пригоду в фентезійному світі як слизовий монстр із унікальними навичками.",
          "popularity": 166.06,
          "poster_path": "/9YcNx1dnNkZ3PZzrMqc52WjCEcw.jpg",
          "release_date": "2024-05-17",
          "tagline": "",
          "title": "Коли я переродився слизом",
          "video": false,
          "vote_average": 8.5,
          "vote_count": 710
        },
        {
          "adult": false,
          "backdrop_path": "/mnNkpQ4J9bNubFQfReaI9SVV9QR.jpg",
          "genre_ids": [
            10759,
            10765,
            16,
            35
          ],
          "id": 80504,
          "isKlio": false,
          "original_language": "ja",
          "original_title": "ゆらぎ荘の幽奈さん",
          "overview": "Фуюзора Когараші має здібність бачити надприродне та з самого дитинства одержимий духами. Це спричиняло чимало негараздів упродовж всього його життя, але він навчився боротися зі злими духами! Наразі він бідний, бездомний, та сповнений надій на краще життя в старшій школі. У пошуках прихистку він стикається з маєтком Юраґі, який колись був відомим курортом із гарячими джерелами, але наразі є дешевим та малопопулярним через чутки про примару, яка мешкає там, духа учениці, чий труп було знайдено там. Коґараші вважає, що це не має стати для нього проблемою, а решта мешканців - сексуальні дівчата. Розслабляючись у гарячих джерелах, він міркує щодо проблеми маєтку. Примара маєтку Юраґі —  16-річна школярка Юна, яка сидить у своїй кімнаті. Коґараші не хоче шкодити їй і вирішує допомогти їй розібратися з її незакінченою справою і упокоїтися з миром до того, як вона перетвориться на злого духа. І як тільки з Юною все стає зрозуміло —  відкриваються надприродні секрети інших мешканців маєтку, тож життя нашого героя в Юраґі не обіцяє бути звичайним та спокійним.",
          "popularity": 33.936,
          "poster_path": "/uYSBtQcA9okBKrtahzqOrpw1tdd.jpg",
          "release_date": "2018-09-29",
          "tagline": "",
          "title": "Юна з маєтку Юраґі",
          "video": false,
          "vote_average": 7.5,
          "vote_count": 35
        },
        {
          "adult": false,
          "backdrop_path": "/cHrRSB5cfAvadLpS1zte2fn1DRr.jpg",
          "genre_ids": [
            16,
            35,
            18,
            10765
          ],
          "id": 62157,
          "isKlio": false,
          "original_language": "ja",
          "original_title": "純潔のマリア",
          "overview": "Могутня молода відьма Марія живе з двома своїми фамільярами в Середньовічній Франції часів Столітньої Війни з Англією. Війна в розпалі і Марії набридає просто спостерігати, вона використовує магію в спробі запобігти розвитку конфлікту сподіваючись встановити мир.",
          "popularity": 52.453,
          "poster_path": "/smRcjzhHxtazThHXf9pjfY9gisQ.jpg",
          "release_date": "2015-03-29",
          "tagline": "",
          "title": "Непорочна Марія",
          "video": false,
          "vote_average": 5.889,
          "vote_count": 18
        },
        {
          "adult": false,
          "backdrop_path": "/zQOjsBkOaK2qV9GCVWyh2Pug3EF.jpg",
          "genre_ids": [
            16,
            10765
          ],
          "id": 83238,
          "isKlio": false,
          "original_language": "ja",
          "original_title": "イングレス",
          "overview": "Учені відкрили таємничу речовину, яка може безпосередньо взаємодіяти з людським мозком. Ця речовина, названа \"Екзотична Матерія (XM)\", існувала з найдавніших часів і впливала на людську свідомість і прогрес людства. Після цього відкриття розв'язалася битва між націями і гігантськими корпораціями. Організації по всьому світу розпочали таємну гонку для використання XM. Вона є як можливістю, так і загрозою для людства. Дві фракції прагнуть керувати XM. «Просвітлені» розглядають XM як подарунок, що збагачує людський досвід і сприяє відкриттям. «Опір» бачить XM як вороже захоплення людського розуму. XM і таємниця, прихована за нею, лежить в центрі цієї битви за долю людства.",
          "popularity": 22.175,
          "poster_path": "/nk8m8uwYzP6QICELQS34UtHsWH7.jpg",
          "release_date": "2018-10-18",
          "tagline": "",
          "title": "Інґрес",
          "video": false,
          "vote_average": 6.917,
          "vote_count": 24
        },
        {
          "adult": false,
          "backdrop_path": "/cwUsP3Krqjq98N099SlUaZ2AGZ1.jpg",
          "genre_ids": [
            35,
            16
          ],
          "id": 80613,
          "isKlio": false,
          "original_language": "ja",
          "original_title": "Back Street Girls -ゴクドルズ-",
          "overview": "Японський мультсеріал про життя трьох чоловіків-якудза, яких їхній бос змусив стати жіночим гуртом поп-ідолів.",
          "popularity": 35.525,
          "poster_path": "/kEdDC69YO2Jdau9prfYmJIFFJJ9.jpg",
          "release_date": "2018-09-04",
          "tagline": "",
          "title": "Дівки з задвірків",
          "video": false,
          "vote_average": 6.053,
          "vote_count": 38
        },
        {
          "adult": false,
          "backdrop_path": "/tRtkUNrF8LXcVZap3LGXMChjVvm.jpg",
          "genre_ids": [
            16,
            35
          ],
          "id": 86836,
          "isKlio": false,
          "original_language": "ja",
          "original_title": "なんでここに先生が!?",
          "overview": "17-річний Ічіро Сато — звичайний підліток, який завжди опиняється в пікантних ситуаціях із молодою привабливою вчителькою Каною Коджімою і щоразу, з кожною збоченою історією, їхній зв’язок міцнішає, переростаючи в дещо більше.",
          "popularity": 70.412,
          "poster_path": "/qBbXn8dECRo9eDscmpDg9pcuP8U.jpg",
          "release_date": "2019-06-24",
          "tagline": "",
          "title": "Чому ви тут, учителько?!",
          "video": false,
          "vote_average": 8.501,
          "vote_count": 643
        }
      ]
    }
  ]
}